pretix_sepadebit/__init__.py
pretix_sepadebit/apps.py
pretix_sepadebit/bicdata.py
pretix_sepadebit/exporters.py
pretix_sepadebit/models.py
pretix_sepadebit/payment.py
pretix_sepadebit/signals.py
pretix_sepadebit/urls.py
pretix_sepadebit/views.py
pretix_sepadebit/locale/django.pot
pretix_sepadebit/locale/ar/LC_MESSAGES/django.mo
pretix_sepadebit/locale/ar/LC_MESSAGES/django.po
pretix_sepadebit/locale/ca/LC_MESSAGES/django.mo
pretix_sepadebit/locale/ca/LC_MESSAGES/django.po
pretix_sepadebit/locale/cs/LC_MESSAGES/django.mo
pretix_sepadebit/locale/cs/LC_MESSAGES/django.po
pretix_sepadebit/locale/da/LC_MESSAGES/django.mo
pretix_sepadebit/locale/da/LC_MESSAGES/django.po
pretix_sepadebit/locale/de/LC_MESSAGES/django.mo
pretix_sepadebit/locale/de/LC_MESSAGES/django.po
pretix_sepadebit/locale/de_Informal/.gitkeep
pretix_sepadebit/locale/de_Informal/LC_MESSAGES/django.mo
pretix_sepadebit/locale/de_Informal/LC_MESSAGES/django.po
pretix_sepadebit/locale/el/LC_MESSAGES/django.mo
pretix_sepadebit/locale/el/LC_MESSAGES/django.po
pretix_sepadebit/locale/es/LC_MESSAGES/django.mo
pretix_sepadebit/locale/es/LC_MESSAGES/django.po
pretix_sepadebit/locale/fi/LC_MESSAGES/django.mo
pretix_sepadebit/locale/fi/LC_MESSAGES/django.po
pretix_sepadebit/locale/fr/LC_MESSAGES/django.mo
pretix_sepadebit/locale/fr/LC_MESSAGES/django.po
pretix_sepadebit/locale/hr/LC_MESSAGES/django.mo
pretix_sepadebit/locale/hr/LC_MESSAGES/django.po
pretix_sepadebit/locale/it/LC_MESSAGES/django.mo
pretix_sepadebit/locale/it/LC_MESSAGES/django.po
pretix_sepadebit/locale/ja/LC_MESSAGES/django.mo
pretix_sepadebit/locale/ja/LC_MESSAGES/django.po
pretix_sepadebit/locale/lv/LC_MESSAGES/django.mo
pretix_sepadebit/locale/lv/LC_MESSAGES/django.po
pretix_sepadebit/locale/nl/LC_MESSAGES/django.mo
pretix_sepadebit/locale/nl/LC_MESSAGES/django.po
pretix_sepadebit/locale/nl_Informal/LC_MESSAGES/django.mo
pretix_sepadebit/locale/nl_Informal/LC_MESSAGES/django.po
pretix_sepadebit/locale/pl/LC_MESSAGES/django.mo
pretix_sepadebit-2.7.0.dist-info/licenses/LICENSE
pretix_sepadebit-2.7.0.dist-info/METADATA
pretix_sepadebit-2.7.0.dist-info/WHEEL
pretix_sepadebit-2.7.0.dist-info/entry_points.txt
pretix_sepadebit-2.7.0.dist-info/top_level.txt
pretix_sepadebit-2.7.0.dist-info/RECORD
