Metadata-Version: 2.4
Name: pretix-sepadebit
Version: 2.7.0
Summary: This plugin adds SEPA direct debit support to pretix
Author-email: pretix team <support@pretix.eu>
Maintainer-email: pretix team <support@pretix.eu>
License: Copyright 2017 Raphael Michel
Project-URL: homepage, https://pretix.eu
Project-URL: repository, https://github.com/pretix/pretix-sepadebit.git
Keywords: pretix
Requires-Python: >=3.9
License-File: LICENSE
Requires-Dist: django-localflavor
Requires-Dist: sepaxml>=2.4.1
Dynamic: license-file
